random_walk_env/__init__.py
random_walk_env/envs/__init__.py
random_walk_env/envs/random_walk.py
random_walk_env-0.0.4.dist-info/METADATA
random_walk_env-0.0.4.dist-info/WHEEL
random_walk_env-0.0.4.dist-info/licenses/LICENSE
random_walk_env-0.0.4.dist-info/RECORD
