Metadata-Version: 2.3
Name: random_walk_env
Version: 0.0.4
Summary: A random walk environment for Gymnasium
License-File: LICENSE
Requires-Dist: gymnasium
Requires-Dist: pre-commit
